<?xml version="1.0" encoding="utf-8"?><Defs>

<SoundDef>
        <defName>WF_SlashDash_Sound</defName>
        <context>MapOnly</context>
        <eventNames/>
        <maxSimultaneous>1</maxSimultaneous>
        <subSounds>
            <li>
                <grains>
                    <li Class="AudioGrain_Clip">
                        <clipPath>Abilities/Milkwater_Excalibur_Slash_Dash</clipPath>
                    </li>
                </grains>
                <volumeRange>
                    <min>35</min>
                    <max>40</max>
                </volumeRange>
                <pitchRange>
                    <min>1.2</min>
                    <max>1.25</max>
                </pitchRange>
                <sustainLoop>False</sustainLoop>
            </li>
        </subSounds>
</SoundDef>

<SoundDef>
        <defName>WF_RadialBlind_Sound</defName>
        <context>MapOnly</context>
        <eventNames/>
        <maxSimultaneous>1</maxSimultaneous>
        <subSounds>
            <li>
                <grains>
                    <li Class="AudioGrain_Clip">
                        <clipPath>Abilities/Milkwater_Excalibur_Radial_Blind</clipPath>
                    </li>
                </grains>
                <volumeRange>
                    <min>35</min>
                    <max>40</max>
                </volumeRange>
                <pitchRange>
                    <min>1.2</min>
                    <max>1.25</max>
                </pitchRange>
                <sustainLoop>False</sustainLoop>
            </li>
        </subSounds>
</SoundDef>

<SoundDef>
        <defName>WF_RadialJavelin_Sound</defName>
        <context>MapOnly</context>
        <eventNames/>
        <maxSimultaneous>1</maxSimultaneous>
        <subSounds>
            <li>
                <grains>
                    <li Class="AudioGrain_Clip">
                        <clipPath>Abilities/Milkwater_Excalibur_Radial_Javelin</clipPath>
                    </li>
                </grains>
                <volumeRange>
                    <min>35</min>
                    <max>40</max>
                </volumeRange>
                <pitchRange>
                    <min>1.2</min>
                    <max>1.25</max>
                </pitchRange>
                <sustainLoop>False</sustainLoop>
            </li>
        </subSounds>
</SoundDef>

<SoundDef>
        <defName>WF_ExaltedBlade_Sound</defName>
        <context>MapOnly</context>
        <eventNames/>
        <maxSimultaneous>1</maxSimultaneous>
        <subSounds>
            <li>
                <grains>
                    <li Class="AudioGrain_Clip">
                        <clipPath>Abilities/Milkwater_Excalibur_Exalted_Blade</clipPath>
                    </li>
                </grains>
                <volumeRange>
                    <min>35</min>
                    <max>40</max>
                </volumeRange>
                <pitchRange>
                    <min>1.2</min>
                    <max>1.25</max>
                </pitchRange>
                <sustainLoop>False</sustainLoop>
            </li>
        </subSounds>
</SoundDef>

</Defs>
